ccm15/CCM15Device.py
ccm15/CCM15DeviceState.py
ccm15/CCM15SlaveDevice.py
ccm15/__init__.py
py_ccm15_2025-0.1.0.dist-info/LICENSE
py_ccm15_2025-0.1.0.dist-info/METADATA
py_ccm15_2025-0.1.0.dist-info/WHEEL
py_ccm15_2025-0.1.0.dist-info/top_level.txt
py_ccm15_2025-0.1.0.dist-info/RECORD
