Metadata-Version: 2.1
Name: py-ccm15-2025
Version: 0.1.0
Summary: A package to control Midea CCM15 data converter modules
Home-page: https://github.com/MosheL/py-ccm15
Author: Oscar Calvo
Author-email: oscar@calvonet.com
License: UNKNOWN
Platform: UNKNOWN
Classifier: Programming Language :: Python :: 3
Classifier: License :: OSI Approved :: MIT License
Classifier: Operating System :: OS Independent
Requires-Dist: httpx>=0.24.1
Requires-Dist: xmltodict>=0.13.0
Requires-Dist: aiohttp>=3.8.5
